vibe/_version.py
vibe_soren_n-0.5.1.dist-info/METADATA
vibe_soren_n-0.5.1.dist-info/WHEEL
vibe_soren_n-0.5.1.dist-info/entry_points.txt
vibe_soren_n-0.5.1.dist-info/licenses/LICENSE
vibe_soren_n-0.5.1.dist-info/RECORD
