Metadata-Version: 2.4
Name: vibe-soren-n
Version: 0.5.1
Summary: A CLI tool for vibe coding with intelligent workflow orchestration
License-File: LICENSE
Requires-Python: >=3.13
Requires-Dist: click>=8.1.0
Requires-Dist: jsonschema>=4.20.0
Requires-Dist: pydantic>=2.0.0
Requires-Dist: pyyaml>=6.0.0
Requires-Dist: rich>=13.0.0
Requires-Dist: typing-extensions>=4.0.0
Requires-Dist: watchdog>=6.0.0
